dictionizr/__init__.py
dictionizr/conftest.py
dictionizr/dictionizr.py
tests/__init__.py
tests/complex_dictionizr_test.py
tests/dictionizr_test.py
tests/utils/__init__.py
tests/utils/utils.py
dictionizr-1.0.3.dist-info/LICENSE
dictionizr-1.0.3.dist-info/METADATA
dictionizr-1.0.3.dist-info/WHEEL
dictionizr-1.0.3.dist-info/top_level.txt
dictionizr-1.0.3.dist-info/RECORD
