Metadata-Version: 2.1
Name: dictionizr
Version: 1.0.3
Summary: A small package to convert custom python objects to dictionaries and back again
Home-page: https://github.com/joeriddles/dictionizr
Author: Joseph Riddle
Author-email: joeriddles10@gmail.com
License: UNKNOWN
Platform: UNKNOWN
Classifier: Programming Language :: Python :: 3
Classifier: License :: OSI Approved :: MIT License
Classifier: Operating System :: OS Independent
Requires-Python: >=3.6
